02_mux_2.1/rtl/mux_2to1.v
module mux_2to1 (
    input a,
    input b,
    input s,
    output y
);

assign y = ((~s & a) | (s & b));

endmodule

02_mux_2.1/tb/mux_2to1_tb.v
module mux_2to1_tb;

reg a;
reg b;
reg s;
wire y;

mux_2to1 dut(
    .a(a),
    .b(b),
    .s(s),
    .y(y)
);

initial begin
    $dumpfile("mux_2to1.vcd");
    $dumpvars(0, mux_2to1_tb );

    $monitor("Time=%0t a=%b b=%b s=%b y=%b", $time, a, b, s, y);

    //test vector 1: 000
    a = 0; b = 0; s = 0;

    //test vector 2: 010
    #10; a = 0; b = 1; s = 0;

    //test vector 3: 100
    #10; a = 1; b = 0; s = 0;

    //test vector 4: 110
    #10; a = 1; b = 1; s = 0;

    //test vector 5: 001
    #10; a = 0; b = 0; s = 1;

    //test vector 6: 011
    #10; a = 0; b = 1; s = 1;

    //test vector 7: 101
    #10; a = 1; b = 0; s = 1;

    //test vector 8: 111
    #10; a = 1; b = 1; s = 1; 

    #10; $finish;

end
endmodule

02_mux_2.1/mux_2to1.vcd
$date
	Sun Aug 16 21:09:50 2026
$end
$version
	Icarus Verilog
$end
$timescale
	1s
$end
$scope module mux_2to1_tb $end
$var wire 1 ! y $end
$var reg 1 " a $end
$var reg 1 # b $end
$var reg 1 $ s $end
$scope module dut $end
$var wire 1 " a $end
$var wire 1 # b $end
$var wire 1 $ s $end
$var wire 1 ! y $end
$upscope $end
$upscope $end
$enddefinitions $end
#0
$dumpvars
0$
0#
0"
0!
$end
#10
1#
#20
1!
0#
1"
#30
1#
#40
0!
1$
0#
0"
#50
1!
1#
#60
0!
0#
1"
#70
1!
1#
