04_full_adder/rtl/full_adder.v
module full_adder(
    input a,
    input b,
    input cin,
    output sum1,
    output carry1,
    output sum,
    output carry2,
    output cout
);

assign sum1 = a^b;
assign carry1 = a&b;
assign sum = sum1 ^ cin;
assign carry2 = sum1 & cin;
assign cout = carry1 | carry2;

endmodule;

04_full_adder/tb/full_adder_tb.v
module full_adder_tb;

reg a;
reg b;
reg cin;
wire sum1;
wire carry1;
wire carry2;
wire sum;
wire cout;

full_adder dut(
    .a(a),
    .b(b),
    .cin(cin),
    .sum1(sum1),
    .carry1(carry1),
    .carry2(carry2),
    .sum(sum),
    .cout(cout)
);

initial begin
    $dumpfile("full_adder.vcd");
    $dumpvars(0, full_adder_tb);

    $monitor("Time=%0t a=%b b=%b cin=%b sum1=%b carry1=%b carry2=%b sum=%b cout=%b", $time, a, b, cin, sum1, carry1, carry2, sum, cout);

    //test vector1
    a = 0; b = 0; cin = 0; #10;

    //test vector2
    a = 0; b = 0; cin = 1; #10;

    //test vector3
    a = 0; b = 1; cin = 0; #10;

    //test vector4
    a = 0; b = 1; cin  = 1; #10;

    //test vector5
    a = 1; b = 0; cin = 0; #10;

    //test vector6
    a = 1; b = 0; cin = 1; #10;

    //test vector7
     a = 1; b = 1; cin = 0; #10;

    //test vector8
    a = 1; b = 1; cin = 1; #10;

    $finish;

end
endmodule

04_full_adder/full_adder.vcd
$date
	Tue Aug 18 16:31:44 2026
$end
$version
	Icarus Verilog
$end
$timescale
	1s
$end
$scope module full_adder_tb $end
$var wire 1 ! sum1 $end
$var wire 1 " sum $end
$var wire 1 # cout $end
$var wire 1 $ carry2 $end
$var wire 1 % carry1 $end
$var reg 1 & a $end
$var reg 1 ' b $end
$var reg 1 ( cin $end
$scope module dut $end
$var wire 1 & a $end
$var wire 1 ' b $end
$var wire 1 % carry1 $end
$var wire 1 $ carry2 $end
$var wire 1 ( cin $end
$var wire 1 # cout $end
$var wire 1 " sum $end
$var wire 1 ! sum1 $end
$upscope $end
$upscope $end
$enddefinitions $end
#0
$dumpvars
0(
0'
0&
0%
0$
0#
0"
0!
$end
#10
1"
1(
#20
1!
0(
1'
#30
1#
0"
1$
1(
#40
0#
1"
0$
0(
0'
1&
#50
1#
0"
1$
1(
#60
0$
0!
1%
0(
1'
#70
1"
1(
