07_mux_4.1/rtl/mux_4to1.v
module mux_4to1(
    input a,
    input b,
    input c,
    input d,
    input s0,
    input s1,
    output reg y
);

always @(*) begin
    case({s1,s0})
    2'b00: y = a;
    2'b01: y = b;
    2'b10: y = c;
    2'b11: y = d;
    endcase
end
endmodule

07_mux_4.1/tb/mux_4to1_tb.v
`timescale 1ns/1ps

module mux_4to1_tb;

reg a,b,c,d;
wire y;
reg s0,s1;

reg expected;
integer i;

//dut
mux_4to1 dut(
    .a(a),
    .b(b),
    .c(c),
    .d(d),
    .s0(s0),
    .s1(s1),
    .y(y)
);

initial begin
 $dumpfile("waveform/mux_4to1.vcd");
    $dumpvars(0, mux_4to1_tb);

    for (i = 0; i < 64; i++) begin
        {a, b, c, d, s0,s1} = i;
        #10;

//calculating expected output
        case ({s1,s0})
    2'b00: expected = a;
    2'b01: expected = b;
    2'b10: expected = c;
    2'b11: expected = d;
    endcase

//comparing actual output with expected output
    if(y == expected)
    $display("PASS | a=%b b=%b c=%b d=%b | s0=%b s1=%b | y=%b", a, b, c, d, s0, s1, y);
    else
    $display("FAIL | a=%b b=%b c=%b d=%b | s0=%b s1=%b | y=%b expected=%b", a, b, c, d, s0, s1, y,expected);
    
end
$finish;
end
endmodule

07_mux_4.1/waveform/mux_4to1.vcd
$date
	Thu Sep 17 19:40:46 2026
$end
$version
	Icarus Verilog
$end
$timescale
	1ps
$end
$scope module mux_4to1_tb $end
$var wire 1 ! y $end
$var reg 1 " a $end
$var reg 1 # b $end
$var reg 1 $ c $end
$var reg 1 % d $end
$var reg 1 & expected $end
$var reg 1 ' s0 $end
$var reg 1 ( s1 $end
$var integer 32 ) i [31:0] $end
$scope module dut $end
$var wire 1 " a $end
$var wire 1 # b $end
$var wire 1 $ c $end
$var wire 1 % d $end
$var wire 1 ' s0 $end
$var wire 1 ( s1 $end
$var reg 1 ! y $end
$upscope $end
$upscope $end
$enddefinitions $end
#0
$dumpvars
b0 )
0(
0'
x&
0%
0$
0#
0"
0!
$end
#10000
1(
b1 )
0&
#20000
1'
0(
b10 )
#30000
1(
b11 )
#40000
1%
0'
0(
b100 )
#50000
1(
b101 )
#60000
1'
0(
b110 )
#70000
1!
1(
b111 )
#80000
0!
1$
0%
0'
0(
b1000 )
1&
#90000
1!
1(
b1001 )
0&
#100000
0!
1'
0(
b1010 )
1&
#110000
1(
b1011 )
0&
#120000
1%
0'
0(
b1100 )
#130000
1!
1(
b1101 )
#140000
0!
1'
0(
b1110 )
1&
#150000
1!
1(
b1111 )
0&
#160000
0!
1#
0$
0%
0'
0(
b10000 )
1&
#170000
1(
b10001 )
0&
#180000
1!
1'
0(
b10010 )
#190000
0!
1(
b10011 )
1&
#200000
1%
0'
0(
b10100 )
0&
#210000
1(
b10101 )
#220000
1!
1'
0(
b10110 )
#230000
1(
b10111 )
1&
#240000
0!
1$
0%
0'
0(
b11000 )
#250000
1!
1(
b11001 )
0&
#260000
1'
0(
b11010 )
1&
#270000
0!
1(
b11011 )
#280000
1%
0'
0(
b11100 )
0&
#290000
1!
1(
b11101 )
#300000
1'
0(
b11110 )
1&
#310000
1(
b11111 )
#320000
1"
0#
0$
0%
0'
0(
b100000 )
#330000
0!
1(
b100001 )
#340000
1'
0(
b100010 )
0&
#350000
1(
b100011 )
#360000
1!
1%
0'
0(
b100100 )
#370000
0!
1(
b100101 )
1&
#380000
1'
0(
b100110 )
0&
#390000
1!
1(
b100111 )
#400000
1$
0%
0'
0(
b101000 )
1&
#410000
1(
b101001 )
#420000
0!
1'
0(
b101010 )
#430000
1(
b101011 )
0&
#440000
1!
1%
0'
0(
b101100 )
#450000
1(
b101101 )
1&
#460000
0!
1'
0(
b101110 )
#470000
1!
1(
b101111 )
0&
#480000
1#
0$
0%
0'
0(
b110000 )
1&
#490000
0!
1(
b110001 )
#500000
1!
1'
0(
b110010 )
0&
#510000
0!
1(
b110011 )
1&
#520000
1!
1%
0'
0(
b110100 )
0&
#530000
0!
1(
b110101 )
1&
#540000
1!
1'
0(
b110110 )
0&
#550000
1(
b110111 )
1&
#560000
1$
0%
0'
0(
b111000 )
#570000
1(
b111001 )
#580000
1'
0(
b111010 )
#590000
0!
1(
b111011 )
#600000
1!
1%
0'
0(
b111100 )
0&
#610000
1(
b111101 )
1&
#620000
1'
0(
b111110 )
#630000
1(
b111111 )
#640000
b1000000 )
