06_full_subtractor/rtl/full_sub.v
//this full subtractor is made by using two half subtractor circuits...

//half subtractor
module half_sub(
    input a,
    input b,
    output diff,
    output borrow
);

assign diff = a ^ b;
assign borrow = (~a) & b;

endmodule

//full subtractor
module full_sub(
    input a,
    input b,
    input bin,
    output d,
    output bout
);

wire d1, b1, b2;

//first half subtractor
half_sub HS1(
    .a(a),
    .b(b),
    .diff(d1),
    .borrow(b1)
);

//second half subtractor
half_sub HS2(
    .a(d1),
    .b(bin),
    .diff(d),
    .borrow(b2)
);

//final borrow
assign bout = b1 | b2;
endmodule

06_full_subtractor/tb/full_sub_tb.v
module full_sub_tb;

reg a, b, bin;
wire d, bout;
integer i;

full_sub dut(
    .a(a),
    .b(b),
    .bin(bin),
    .d(d),
    .bout(bout)
);

initial begin
    $dumpfile("full_sub.vcd");
    $dumpvars(0, full_sub_tb);

    $monitor("Time=%0t a=%b b=%b bin=%b d=%b bout=%b", $time, a, b, bin, d, bout);

    for(i=0; i<8; i++) begin
        {a, b, bin} = i;
        #10;
    end

    $finish;

end
endmodule

06_full_subtractor/full_sub.vcd
$date
	Wed Sep 16 19:37:27 2026
$end
$version
	Icarus Verilog
$end
$timescale
	1s
$end
$scope module full_sub_tb $end
$var wire 1 ! d $end
$var wire 1 " bout $end
$var reg 1 # a $end
$var reg 1 $ b $end
$var reg 1 % bin $end
$var integer 32 & i [31:0] $end
$scope module dut $end
$var wire 1 # a $end
$var wire 1 $ b $end
$var wire 1 % bin $end
$var wire 1 " bout $end
$var wire 1 ' d1 $end
$var wire 1 ! d $end
$var wire 1 ( b2 $end
$var wire 1 ) b1 $end
$scope module HS1 $end
$var wire 1 # a $end
$var wire 1 $ b $end
$var wire 1 ) borrow $end
$var wire 1 ' diff $end
$upscope $end
$scope module HS2 $end
$var wire 1 ' a $end
$var wire 1 % b $end
$var wire 1 ( borrow $end
$var wire 1 ! diff $end
$upscope $end
$upscope $end
$upscope $end
$enddefinitions $end
#0
$dumpvars
0)
0(
0'
b0 &
0%
0$
0#
0"
0!
$end
#10
1"
1!
1(
1%
b1 &
#20
1'
1)
1!
0(
1$
0%
b10 &
#30
0!
1%
b11 &
#40
0"
0)
1!
1#
0$
0%
b100 &
#50
0!
1%
b101 &
#60
0'
0!
1$
0%
b110 &
#70
1"
1!
1(
1%
b111 &
#80
b1000 &
